modlib/__init__.py
modlib/apps/__init__.py
modlib/apps/annotate.py
modlib/apps/area.py
modlib/apps/blur.py
modlib/apps/calculate.py
modlib/apps/heatmap.py
modlib/apps/matcher.py
modlib/apps/motion.py
modlib/apps/object_counter.py
modlib/apps/tracker/__init__.py
modlib/apps/tracker/basetrack.py
modlib/apps/tracker/byte_tracker.py
modlib/apps/tracker/kalman_filter.py
modlib/apps/tracker/matching.py
modlib/devices/__init__.py
modlib/devices/device.py
modlib/devices/frame.py
modlib/devices/sources.py
modlib/devices/ai_camera/__init__.py
modlib/devices/ai_camera/ai_camera.py
modlib/devices/ai_camera/allocator.py
modlib/devices/ai_camera/camera_manager.py
modlib/devices/ai_camera/imx500.py
modlib/devices/ai_camera/libcamera_config.py
modlib/devices/ai_camera/rpk_packager.py
modlib/devices/ai_camera/utils.py
modlib/devices/ai_camera/v4l2.py
modlib/devices/interpreters/__init__.py
modlib/devices/interpreters/keras_interpreter.py
modlib/devices/interpreters/onnx_interpreter.py
modlib/devices/playback/__init__.py
modlib/devices/playback/codecs.py
modlib/devices/playback/playback.py
modlib/devices/playback/recorder.py
modlib/devices/triton/README.md
modlib/devices/triton/__init__.py
modlib/devices/triton/allocator.py
modlib/devices/triton/arena_path_resolver.py
modlib/devices/triton/meson.build
modlib/devices/triton/request_interface.py
modlib/devices/triton/triton.py
modlib/devices/triton/triton_cpp.cpython-311-aarch64-linux-gnu.so
modlib/devices/triton/cpp/IMX501Utils.cpp
modlib/devices/triton/cpp/binding.cpp
modlib/devices/triton/cpp/parser.cpp
modlib/devices/triton/cpp/triton.cpp
modlib/devices/triton/cpp/include/IMX501Utils.h
modlib/devices/triton/cpp/include/apParams.flatbuffers_generated.h
modlib/devices/triton/cpp/include/parser.h
modlib/devices/triton/cpp/include/progress_bar.h
modlib/devices/triton/cpp/include/triton.h
modlib/devices/triton/cpp/vendors/flatbuffers-1.11.0/LICENSE.txt
modlib-1.3.1.dist-info/METADATA
modlib-1.3.1.dist-info/WHEEL
modlib-1.3.1.dist-info/RECORD
modlib-1.3.1.dist-info/sboms/auditwheel.cdx.json
