Metadata-Version: 2.1
Name: modlib
Version: 1.3.1
Author: Sony Semiconductor Solutions Corp
Classifier: License :: OSI Approved :: Apache Software License
Classifier: Programming Language :: C++
Classifier: Programming Language :: Python
Classifier: Programming Language :: Python :: 3
Classifier: Programming Language :: Python :: 3.11
Classifier: Programming Language :: Python :: 3.12
Classifier: Programming Language :: Python :: 3.13
Requires-Python: <3.14,>=3.11
Requires-Dist: lapx~=0.9.2
Requires-Dist: numpy<=2.3.5,>=1.26.0
Requires-Dist: opencv-python<=4.12.0.88,>=4.10.0.84
Requires-Dist: libarchive-c~=5.3
Requires-Dist: requests~=2.32.5
Requires-Dist: tqdm~=4.67.1
